pabot/__init__.py
pabot-0.1.0.dist-info/METADATA
pabot-0.1.0.dist-info/WHEEL
pabot-0.1.0.dist-info/top_level.txt
pabot-0.1.0.dist-info/RECORD
